teraflopai_data/__init__.py
teraflopai_data/pipeline.py
teraflopai_data/clients/ray_client.py
teraflopai_data/components/__init__.py
teraflopai_data/components/distributed_base.py
teraflopai_data/components/image/aesthetic.py
teraflopai_data/components/image/blur.py
teraflopai_data/components/image/caption.py
teraflopai_data/components/image/embedding.py
teraflopai_data/components/image/image_hashing.py
teraflopai_data/components/image/nsfw.py
teraflopai_data/components/image/watermark.py
teraflopai_data/components/text/embedding.py
teraflopai_data/components/text/fineweb_edu.py
teraflopai_data/components/video/frame_extractor.py
teraflopai_data/components/video/video_segmentation.py
teraflopai_data/models/owl_watermark.py
teraflopai_data-0.1.1.dist-info/licenses/LICENSE
teraflopai_data-0.1.1.dist-info/METADATA
teraflopai_data-0.1.1.dist-info/WHEEL
teraflopai_data-0.1.1.dist-info/top_level.txt
teraflopai_data-0.1.1.dist-info/RECORD
